{
  "shard": 4,
  "count": 80,
  "items": [
    {
      "doc": "ISO-2859-1",
      "file": "fig-p69-1.png",
      "type": "figure",
      "label": null,
      "page": 69,
      "render": null,
      "path": "C:/Users/david.kuo/SterileGMP-Knowledge-Hub/ISO/ISO-2859-1/figures-thumb/fig-p69-1.png",
      "used_thumb": true
    },
    {
      "doc": "ISO-2859-1",
      "file": "fig-p70-1.png",
      "type": "figure",
      "label": null,
      "page": 70,
      "render": null,
      "path": "C:/Users/david.kuo/SterileGMP-Knowledge-Hub/ISO/ISO-2859-1/figures-thumb/fig-p70-1.png",
      "used_thumb": true
    },
    {
      "doc": "ISO-2859-1",
      "file": "fig-p71-1.png",
      "type": "figure",
      "label": null,
      "page": 71,
      "render": null,
      "path": "C:/Users/david.kuo/SterileGMP-Knowledge-Hub/ISO/ISO-2859-1/figures-thumb/fig-p71-1.png",
      "used_thumb": true
    },
    {
      "doc": "ISO-2859-1",
      "file": "fig-p72-1.png",
      "type": "figure",
      "label": null,
      "page": 72,
      "render": null,
      "path": "C:/Users/david.kuo/SterileGMP-Knowledge-Hub/ISO/ISO-2859-1/figures-thumb/fig-p72-1.png",
      "used_thumb": true
    },
    {
      "doc": "ISO-2859-1",
      "file": "fig-p73-1.png",
      "type": "figure",
      "label": null,
      "page": 73,
      "render": null,
      "path": "C:/Users/david.kuo/SterileGMP-Knowledge-Hub/ISO/ISO-2859-1/figures-thumb/fig-p73-1.png",
      "used_thumb": true
    },
    {
      "doc": "ISO-2859-1",
      "file": "fig-p74-1.png",
      "type": "figure",
      "label": null,
      "page": 74,
      "render": null,
      "path": "C:/Users/david.kuo/SterileGMP-Knowledge-Hub/ISO/ISO-2859-1/figures-thumb/fig-p74-1.png",
      "used_thumb": true
    },
    {
      "doc": "ISO-2859-1",
      "file": "fig-p75-1.png",
      "type": "figure",
      "label": null,
      "page": 75,
      "render": null,
      "path": "C:/Users/david.kuo/SterileGMP-Knowledge-Hub/ISO/ISO-2859-1/figures-thumb/fig-p75-1.png",
      "used_thumb": true
    },
    {
      "doc": "ISO-2859-1",
      "file": "fig-p76-1.png",
      "type": "figure",
      "label": null,
      "page": 76,
      "render": null,
      "path": "C:/Users/david.kuo/SterileGMP-Knowledge-Hub/ISO/ISO-2859-1/figures-thumb/fig-p76-1.png",
      "used_thumb": true
    },
    {
      "doc": "ISO-2859-1",
      "file": "fig-p77-1.png",
      "type": "figure",
      "label": null,
      "page": 77,
      "render": null,
      "path": "C:/Users/david.kuo/SterileGMP-Knowledge-Hub/ISO/ISO-2859-1/figures-thumb/fig-p77-1.png",
      "used_thumb": true
    },
    {
      "doc": "ISO-2859-1",
      "file": "fig-p78-1.png",
      "type": "figure",
      "label": null,
      "page": 78,
      "render": null,
      "path": "C:/Users/david.kuo/SterileGMP-Knowledge-Hub/ISO/ISO-2859-1/figures-thumb/fig-p78-1.png",
      "used_thumb": true
    },
    {
      "doc": "ISO-2859-1",
      "file": "fig-p79-1.png",
      "type": "figure",
      "label": null,
      "page": 79,
      "render": null,
      "path": "C:/Users/david.kuo/SterileGMP-Knowledge-Hub/ISO/ISO-2859-1/figures-thumb/fig-p79-1.png",
      "used_thumb": true
    },
    {
      "doc": "ISO-2859-1",
      "file": "fig-p80-1.png",
      "type": "figure",
      "label": null,
      "page": 80,
      "render": null,
      "path": "C:/Users/david.kuo/SterileGMP-Knowledge-Hub/ISO/ISO-2859-1/figures-thumb/fig-p80-1.png",
      "used_thumb": true
    },
    {
      "doc": "ISO-2859-1",
      "file": "fig-p81-1.png",
      "type": "figure",
      "label": null,
      "page": 81,
      "render": null,
      "path": "C:/Users/david.kuo/SterileGMP-Knowledge-Hub/ISO/ISO-2859-1/figures-thumb/fig-p81-1.png",
      "used_thumb": true
    },
    {
      "doc": "ISO-2859-1",
      "file": "fig-p82-1.png",
      "type": "figure",
      "label": null,
      "page": 82,
      "render": null,
      "path": "C:/Users/david.kuo/SterileGMP-Knowledge-Hub/ISO/ISO-2859-1/figures-thumb/fig-p82-1.png",
      "used_thumb": true
    },
    {
      "doc": "ISO-2859-1",
      "file": "fig-p83-1.png",
      "type": "figure",
      "label": null,
      "page": 83,
      "render": null,
      "path": "C:/Users/david.kuo/SterileGMP-Knowledge-Hub/ISO/ISO-2859-1/figures-thumb/fig-p83-1.png",
      "used_thumb": true
    },
    {
      "doc": "ISO-2859-1",
      "file": "fig-p84-1.png",
      "type": "figure",
      "label": null,
      "page": 84,
      "render": null,
      "path": "C:/Users/david.kuo/SterileGMP-Knowledge-Hub/ISO/ISO-2859-1/figures-thumb/fig-p84-1.png",
      "used_thumb": true
    },
    {
      "doc": "ISO-2859-1",
      "file": "fig-p85-1.png",
      "type": "figure",
      "label": null,
      "page": 85,
      "render": null,
      "path": "C:/Users/david.kuo/SterileGMP-Knowledge-Hub/ISO/ISO-2859-1/figures-thumb/fig-p85-1.png",
      "used_thumb": true
    },
    {
      "doc": "ISO-2859-1",
      "file": "fig-p86-1.png",
      "type": "figure",
      "label": null,
      "page": 86,
      "render": null,
      "path": "C:/Users/david.kuo/SterileGMP-Knowledge-Hub/ISO/ISO-2859-1/figures-thumb/fig-p86-1.png",
      "used_thumb": true
    },
    {
      "doc": "ISO-2859-1",
      "file": "fig-p87-1.png",
      "type": "figure",
      "label": null,
      "page": 87,
      "render": null,
      "path": "C:/Users/david.kuo/SterileGMP-Knowledge-Hub/ISO/ISO-2859-1/figures-thumb/fig-p87-1.png",
      "used_thumb": true
    },
    {
      "doc": "ISO-2859-1",
      "file": "fig-p88-1.png",
      "type": "figure",
      "label": null,
      "page": 88,
      "render": null,
      "path": "C:/Users/david.kuo/SterileGMP-Knowledge-Hub/ISO/ISO-2859-1/figures-thumb/fig-p88-1.png",
      "used_thumb": true
    },
    {
      "doc": "ISO-2859-1",
      "file": "fig-p89-1.png",
      "type": "figure",
      "label": null,
      "page": 89,
      "render": null,
      "path": "C:/Users/david.kuo/SterileGMP-Knowledge-Hub/ISO/ISO-2859-1/figures-thumb/fig-p89-1.png",
      "used_thumb": true
    },
    {
      "doc": "ISO-2859-1",
      "file": "fig-p90-1.png",
      "type": "figure",
      "label": null,
      "page": 90,
      "render": null,
      "path": "C:/Users/david.kuo/SterileGMP-Knowledge-Hub/ISO/ISO-2859-1/figures-thumb/fig-p90-1.png",
      "used_thumb": true
    },
    {
      "doc": "ISO-2859-1",
      "file": "fig-p91-1.png",
      "type": "figure",
      "label": null,
      "page": 91,
      "render": null,
      "path": "C:/Users/david.kuo/SterileGMP-Knowledge-Hub/ISO/ISO-2859-1/figures-thumb/fig-p91-1.png",
      "used_thumb": true
    },
    {
      "doc": "ISO-9000",
      "file": "vec-p39-1.png",
      "type": "figure",
      "label": "Figure A.1",
      "page": 39,
      "render": "fallback",
      "path": "C:/Users/david.kuo/SterileGMP-Knowledge-Hub/ISO/ISO-9000/figures/vec-p39-1.png",
      "used_thumb": false
    },
    {
      "doc": "ISO-9000",
      "file": "vec-p39-2.png",
      "type": "figure",
      "label": "Figure A.2",
      "page": 39,
      "render": "fallback",
      "path": "C:/Users/david.kuo/SterileGMP-Knowledge-Hub/ISO/ISO-9000/figures/vec-p39-2.png",
      "used_thumb": false
    },
    {
      "doc": "ISO-9000",
      "file": "vec-p40-1.png",
      "type": "figure",
      "label": "Figure A.3",
      "page": 40,
      "render": "fallback",
      "path": "C:/Users/david.kuo/SterileGMP-Knowledge-Hub/ISO/ISO-9000/figures/vec-p40-1.png",
      "used_thumb": false
    },
    {
      "doc": "ISO-9000",
      "file": "vec-p40-2.png",
      "type": "figure",
      "label": "Figure A.4",
      "page": 40,
      "render": "fallback",
      "path": "C:/Users/david.kuo/SterileGMP-Knowledge-Hub/ISO/ISO-9000/figures/vec-p40-2.png",
      "used_thumb": false
    },
    {
      "doc": "ISO-9000",
      "file": "vec-p41-1.png",
      "type": "figure",
      "label": "Figure A.5",
      "page": 41,
      "render": "fallback",
      "path": "C:/Users/david.kuo/SterileGMP-Knowledge-Hub/ISO/ISO-9000/figures/vec-p41-1.png",
      "used_thumb": false
    },
    {
      "doc": "ISO-9000",
      "file": "vec-p42-1.png",
      "type": "figure",
      "label": "Figure A.6",
      "page": 42,
      "render": "fallback",
      "path": "C:/Users/david.kuo/SterileGMP-Knowledge-Hub/ISO/ISO-9000/figures/vec-p42-1.png",
      "used_thumb": false
    },
    {
      "doc": "ISO-9000",
      "file": "vec-p43-1.png",
      "type": "figure",
      "label": "Figure A.7",
      "page": 43,
      "render": "fallback",
      "path": "C:/Users/david.kuo/SterileGMP-Knowledge-Hub/ISO/ISO-9000/figures/vec-p43-1.png",
      "used_thumb": false
    },
    {
      "doc": "ISO-9000",
      "file": "vec-p44-1.png",
      "type": "figure",
      "label": "Figure A.8",
      "page": 44,
      "render": "fallback",
      "path": "C:/Users/david.kuo/SterileGMP-Knowledge-Hub/ISO/ISO-9000/figures/vec-p44-1.png",
      "used_thumb": false
    },
    {
      "doc": "ISO-9000",
      "file": "vec-p45-1.png",
      "type": "figure",
      "label": "Figure A.9",
      "page": 45,
      "render": "fallback",
      "path": "C:/Users/david.kuo/SterileGMP-Knowledge-Hub/ISO/ISO-9000/figures/vec-p45-1.png",
      "used_thumb": false
    },
    {
      "doc": "ISO-9000",
      "file": "vec-p46-1.png",
      "type": "figure",
      "label": "Figure A.10",
      "page": 46,
      "render": "fallback",
      "path": "C:/Users/david.kuo/SterileGMP-Knowledge-Hub/ISO/ISO-9000/figures/vec-p46-1.png",
      "used_thumb": false
    },
    {
      "doc": "ISO-9000",
      "file": "vec-p47-1.png",
      "type": "figure",
      "label": "Figure A.11",
      "page": 47,
      "render": "fallback",
      "path": "C:/Users/david.kuo/SterileGMP-Knowledge-Hub/ISO/ISO-9000/figures/vec-p47-1.png",
      "used_thumb": false
    },
    {
      "doc": "ISO-9000",
      "file": "vec-p48-1.png",
      "type": "figure",
      "label": "Figure A.12",
      "page": 48,
      "render": "fallback",
      "path": "C:/Users/david.kuo/SterileGMP-Knowledge-Hub/ISO/ISO-9000/figures/vec-p48-1.png",
      "used_thumb": false
    },
    {
      "doc": "ISO-9000",
      "file": "vec-p49-1.png",
      "type": "figure",
      "label": "Figure A.13",
      "page": 49,
      "render": "fallback",
      "path": "C:/Users/david.kuo/SterileGMP-Knowledge-Hub/ISO/ISO-9000/figures/vec-p49-1.png",
      "used_thumb": false
    },
    {
      "doc": "ISO-9000",
      "file": "vec-p50-1.png",
      "type": "figure",
      "label": "Figure A.14",
      "page": 50,
      "render": "fallback",
      "path": "C:/Users/david.kuo/SterileGMP-Knowledge-Hub/ISO/ISO-9000/figures/vec-p50-1.png",
      "used_thumb": false
    },
    {
      "doc": "ISO-9000",
      "file": "vec-p51-1.png",
      "type": "figure",
      "label": "Figure A.15",
      "page": 51,
      "render": "fallback",
      "path": "C:/Users/david.kuo/SterileGMP-Knowledge-Hub/ISO/ISO-9000/figures/vec-p51-1.png",
      "used_thumb": false
    },
    {
      "doc": "ISO-9000",
      "file": "vec-p52-1.png",
      "type": "figure",
      "label": "Figure A.16",
      "page": 52,
      "render": "fallback",
      "path": "C:/Users/david.kuo/SterileGMP-Knowledge-Hub/ISO/ISO-9000/figures/vec-p52-1.png",
      "used_thumb": false
    },
    {
      "doc": "ISO-9001",
      "file": "tbl-p31-1.png",
      "type": "table",
      "label": "Table A.1",
      "page": 31,
      "render": null,
      "path": "C:/Users/david.kuo/SterileGMP-Knowledge-Hub/ISO/ISO-9001/figures/tbl-p31-1.png",
      "used_thumb": false
    },
    {
      "doc": "ISO-9001",
      "file": "tbl-p37-1.png",
      "type": "table",
      "label": "Table B.1",
      "page": 37,
      "render": null,
      "path": "C:/Users/david.kuo/SterileGMP-Knowledge-Hub/ISO/ISO-9001/figures/tbl-p37-1.png",
      "used_thumb": false
    },
    {
      "doc": "ISO-TR-24971",
      "file": "vec-p15-1.png",
      "type": "figure",
      "label": "Figure 1.",
      "page": 15,
      "render": "fallback",
      "path": "C:/Users/david.kuo/SterileGMP-Knowledge-Hub/ISO/ISO-TR-24971/figures/vec-p15-1.png",
      "used_thumb": false
    },
    {
      "doc": "ISO-TR-24971",
      "file": "vec-p15-2.png",
      "type": "figure",
      "label": "Figure 1",
      "page": 15,
      "render": "fallback",
      "path": "C:/Users/david.kuo/SterileGMP-Knowledge-Hub/ISO/ISO-TR-24971/figures/vec-p15-2.png",
      "used_thumb": false
    },
    {
      "doc": "ISO-TR-24971",
      "file": "vec-p17-1.png",
      "type": "figure",
      "label": "Figure 2",
      "page": 17,
      "render": "fallback",
      "path": "C:/Users/david.kuo/SterileGMP-Knowledge-Hub/ISO/ISO-TR-24971/figures/vec-p17-1.png",
      "used_thumb": false
    },
    {
      "doc": "ISO-TR-24971",
      "file": "vec-p20-2.png",
      "type": "figure",
      "label": "Figure 3",
      "page": 20,
      "render": "fallback",
      "path": "C:/Users/david.kuo/SterileGMP-Knowledge-Hub/ISO/ISO-TR-24971/figures/vec-p20-2.png",
      "used_thumb": false
    },
    {
      "doc": "ISO-TR-24971",
      "file": "vec-p21-1.png",
      "type": "figure",
      "label": "Figure 4",
      "page": 21,
      "render": "fallback",
      "path": "C:/Users/david.kuo/SterileGMP-Knowledge-Hub/ISO/ISO-TR-24971/figures/vec-p21-1.png",
      "used_thumb": false
    },
    {
      "doc": "ISO-TR-24971",
      "file": "vec-p59-1.png",
      "type": "figure",
      "label": "Figure  A.4",
      "page": 59,
      "render": "fallback",
      "path": "C:/Users/david.kuo/SterileGMP-Knowledge-Hub/ISO/ISO-TR-24971/figures/vec-p59-1.png",
      "used_thumb": false
    },
    {
      "doc": "ISO-TR-24971",
      "file": "vec-p18-2.png",
      "type": "figure",
      "label": "Figure C.1",
      "page": 18,
      "render": "fallback",
      "path": "C:/Users/david.kuo/SterileGMP-Knowledge-Hub/ISO/ISO-TR-24971/figures/vec-p18-2.png",
      "used_thumb": false
    },
    {
      "doc": "ISO-TR-24971",
      "file": "vec-p57-1.png",
      "type": "figure",
      "label": "Figure  E.1",
      "page": 57,
      "render": "fallback",
      "path": "C:/Users/david.kuo/SterileGMP-Knowledge-Hub/ISO/ISO-TR-24971/figures/vec-p57-1.png",
      "used_thumb": false
    },
    {
      "doc": "ISO-TR-24971",
      "file": "vec-p58-1.png",
      "type": "figure",
      "label": "Figure E.1",
      "page": 58,
      "render": "fallback",
      "path": "C:/Users/david.kuo/SterileGMP-Knowledge-Hub/ISO/ISO-TR-24971/figures/vec-p58-1.png",
      "used_thumb": false
    },
    {
      "doc": "ISO-TR-24971",
      "file": "vec-p62-2.png",
      "type": "figure",
      "label": "Figure F.1",
      "page": 62,
      "render": "fallback",
      "path": "C:/Users/david.kuo/SterileGMP-Knowledge-Hub/ISO/ISO-TR-24971/figures/vec-p62-2.png",
      "used_thumb": false
    },
    {
      "doc": "ISO-TR-24971",
      "file": "vec-p63-1.png",
      "type": "figure",
      "label": "Figure F.2.",
      "page": 63,
      "render": "fallback",
      "path": "C:/Users/david.kuo/SterileGMP-Knowledge-Hub/ISO/ISO-TR-24971/figures/vec-p63-1.png",
      "used_thumb": false
    },
    {
      "doc": "ISO-TR-24971",
      "file": "vec-p64-1.png",
      "type": "figure",
      "label": "Figure F.2",
      "page": 64,
      "render": "fallback",
      "path": "C:/Users/david.kuo/SterileGMP-Knowledge-Hub/ISO/ISO-TR-24971/figures/vec-p64-1.png",
      "used_thumb": false
    },
    {
      "doc": "ISO-TR-24971",
      "file": "vec-p80-1.png",
      "type": "figure",
      "label": "Figure H.1",
      "page": 80,
      "render": "fallback",
      "path": "C:/Users/david.kuo/SterileGMP-Knowledge-Hub/ISO/ISO-TR-24971/figures/vec-p80-1.png",
      "used_thumb": false
    },
    {
      "doc": "ISO-TR-24971",
      "file": "tbl-p8-1.png",
      "type": "table",
      "label": "Table 1",
      "page": 8,
      "render": null,
      "path": "C:/Users/david.kuo/SterileGMP-Knowledge-Hub/ISO/ISO-TR-24971/figures/tbl-p8-1.png",
      "used_thumb": false
    },
    {
      "doc": "ISO-TR-24971",
      "file": "tbl-p9-1.png",
      "type": "table",
      "label": "Table 1",
      "page": 9,
      "render": null,
      "path": "C:/Users/david.kuo/SterileGMP-Knowledge-Hub/ISO/ISO-TR-24971/figures/tbl-p9-1.png",
      "used_thumb": false
    },
    {
      "doc": "ISO-TR-24971",
      "file": "vec-p19-1.png",
      "type": "table",
      "label": "Table 2",
      "page": 19,
      "render": "fallback",
      "path": "C:/Users/david.kuo/SterileGMP-Knowledge-Hub/ISO/ISO-TR-24971/figures/vec-p19-1.png",
      "used_thumb": false
    },
    {
      "doc": "ISO-TR-24971",
      "file": "vec-p20-1.png",
      "type": "table",
      "label": "Table 3",
      "page": 20,
      "render": "fallback",
      "path": "C:/Users/david.kuo/SterileGMP-Knowledge-Hub/ISO/ISO-TR-24971/figures/vec-p20-1.png",
      "used_thumb": false
    },
    {
      "doc": "ISO-TR-24971",
      "file": "vec-p20-3.png",
      "type": "table",
      "label": "Table 4",
      "page": 20,
      "render": "fallback",
      "path": "C:/Users/david.kuo/SterileGMP-Knowledge-Hub/ISO/ISO-TR-24971/figures/vec-p20-3.png",
      "used_thumb": false
    },
    {
      "doc": "ISO-TR-24971",
      "file": "vec-p18-1.png",
      "type": "table",
      "label": "Table 5.",
      "page": 18,
      "render": "fallback",
      "path": "C:/Users/david.kuo/SterileGMP-Knowledge-Hub/ISO/ISO-TR-24971/figures/vec-p18-1.png",
      "used_thumb": false
    },
    {
      "doc": "ISO-TR-24971",
      "file": "tbl-p21-1.png",
      "type": "table",
      "label": "Table 5",
      "page": 21,
      "render": null,
      "path": "C:/Users/david.kuo/SterileGMP-Knowledge-Hub/ISO/ISO-TR-24971/figures/tbl-p21-1.png",
      "used_thumb": false
    },
    {
      "doc": "ISO-TR-24971",
      "file": "tbl-p23-1.png",
      "type": "table",
      "label": "Table 6",
      "page": 23,
      "render": null,
      "path": "C:/Users/david.kuo/SterileGMP-Knowledge-Hub/ISO/ISO-TR-24971/figures/tbl-p23-1.png",
      "used_thumb": false
    },
    {
      "doc": "ISO-TR-24971",
      "file": "tbl-p31-1.png",
      "type": "table",
      "label": "Table 7",
      "page": 31,
      "render": null,
      "path": "C:/Users/david.kuo/SterileGMP-Knowledge-Hub/ISO/ISO-TR-24971/figures/tbl-p31-1.png",
      "used_thumb": false
    },
    {
      "doc": "ISO-TR-24971",
      "file": "tbl-p32-1.png",
      "type": "table",
      "label": "Table 7",
      "page": 32,
      "render": null,
      "path": "C:/Users/david.kuo/SterileGMP-Knowledge-Hub/ISO/ISO-TR-24971/figures/tbl-p32-1.png",
      "used_thumb": false
    },
    {
      "doc": "ISO-TR-24971",
      "file": "vec-p51-1.png",
      "type": "table",
      "label": "Table C.1",
      "page": 51,
      "render": "fallback",
      "path": "C:/Users/david.kuo/SterileGMP-Knowledge-Hub/ISO/ISO-TR-24971/figures/vec-p51-1.png",
      "used_thumb": false
    },
    {
      "doc": "ISO-TR-24971",
      "file": "vec-p52-1.png",
      "type": "table",
      "label": "Table C.1",
      "page": 52,
      "render": "fallback",
      "path": "C:/Users/david.kuo/SterileGMP-Knowledge-Hub/ISO/ISO-TR-24971/figures/vec-p52-1.png",
      "used_thumb": false
    },
    {
      "doc": "ISO-TR-24971",
      "file": "vec-p61-1.png",
      "type": "table",
      "label": "Table C.2",
      "page": 61,
      "render": "fallback",
      "path": "C:/Users/david.kuo/SterileGMP-Knowledge-Hub/ISO/ISO-TR-24971/figures/vec-p61-1.png",
      "used_thumb": false
    },
    {
      "doc": "ISO-TR-24971",
      "file": "tbl-p63-1.png",
      "type": "table",
      "label": "Table F.1",
      "page": 63,
      "render": null,
      "path": "C:/Users/david.kuo/SterileGMP-Knowledge-Hub/ISO/ISO-TR-24971/figures/tbl-p63-1.png",
      "used_thumb": false
    },
    {
      "doc": "ISO-TR-24971",
      "file": "tbl-p82-1.png",
      "type": "table",
      "label": "Table H.1",
      "page": 82,
      "render": null,
      "path": "C:/Users/david.kuo/SterileGMP-Knowledge-Hub/ISO/ISO-TR-24971/figures/tbl-p82-1.png",
      "used_thumb": false
    },
    {
      "doc": "ISO-TR-24971",
      "file": "tbl-p83-1.png",
      "type": "table",
      "label": "Table H.1",
      "page": 83,
      "render": null,
      "path": "C:/Users/david.kuo/SterileGMP-Knowledge-Hub/ISO/ISO-TR-24971/figures/tbl-p83-1.png",
      "used_thumb": false
    },
    {
      "doc": "ISPE-GAMP5",
      "file": "fig-p12-1.png",
      "type": "figure",
      "label": "Figure 1.1",
      "page": 12,
      "render": null,
      "path": "C:/Users/david.kuo/SterileGMP-Knowledge-Hub/ISPE/ISPE-GAMP5/figures/fig-p12-1.png",
      "used_thumb": false
    },
    {
      "doc": "ISPE-GAMP5",
      "file": "fig-p16-1.png",
      "type": "figure",
      "label": "Figure 1.2",
      "page": 16,
      "render": null,
      "path": "C:/Users/david.kuo/SterileGMP-Knowledge-Hub/ISPE/ISPE-GAMP5/figures-thumb/fig-p16-1.png",
      "used_thumb": true
    },
    {
      "doc": "ISPE-GAMP5",
      "file": "fig-p19-1.png",
      "type": "figure",
      "label": "Figure 2.1",
      "page": 19,
      "render": null,
      "path": "C:/Users/david.kuo/SterileGMP-Knowledge-Hub/ISPE/ISPE-GAMP5/figures/fig-p19-1.png",
      "used_thumb": false
    },
    {
      "doc": "ISPE-GAMP5",
      "file": "fig-p22-1.png",
      "type": "figure",
      "label": "Figure 2.2",
      "page": 22,
      "render": null,
      "path": "C:/Users/david.kuo/SterileGMP-Knowledge-Hub/ISPE/ISPE-GAMP5/figures/fig-p22-1.png",
      "used_thumb": false
    },
    {
      "doc": "ISPE-GAMP5",
      "file": "fig-p25-1.png",
      "type": "figure",
      "label": "Figure 3.1",
      "page": 25,
      "render": null,
      "path": "C:/Users/david.kuo/SterileGMP-Knowledge-Hub/ISPE/ISPE-GAMP5/figures-thumb/fig-p25-1.png",
      "used_thumb": true
    },
    {
      "doc": "ISPE-GAMP5",
      "file": "fig-p26-1.png",
      "type": "figure",
      "label": "Figure 3.2",
      "page": 26,
      "render": null,
      "path": "C:/Users/david.kuo/SterileGMP-Knowledge-Hub/ISPE/ISPE-GAMP5/figures/fig-p26-1.png",
      "used_thumb": false
    },
    {
      "doc": "ISPE-GAMP5",
      "file": "fig-p27-1.png",
      "type": "figure",
      "label": "Figure 3.4",
      "page": 27,
      "render": null,
      "path": "C:/Users/david.kuo/SterileGMP-Knowledge-Hub/ISPE/ISPE-GAMP5/figures/fig-p27-1.png",
      "used_thumb": false
    },
    {
      "doc": "ISPE-GAMP5",
      "file": "fig-p27-2.png",
      "type": "figure",
      "label": "Figure 3.4",
      "page": 27,
      "render": null,
      "path": "C:/Users/david.kuo/SterileGMP-Knowledge-Hub/ISPE/ISPE-GAMP5/figures/fig-p27-2.png",
      "used_thumb": false
    },
    {
      "doc": "ISPE-GAMP5",
      "file": "fig-p29-1.png",
      "type": "figure",
      "label": "Figure 3.5",
      "page": 29,
      "render": null,
      "path": "C:/Users/david.kuo/SterileGMP-Knowledge-Hub/ISPE/ISPE-GAMP5/figures/fig-p29-1.png",
      "used_thumb": false
    },
    {
      "doc": "ISPE-GAMP5",
      "file": "fig-p32-1.png",
      "type": "figure",
      "label": "Figure 4.1",
      "page": 32,
      "render": null,
      "path": "C:/Users/david.kuo/SterileGMP-Knowledge-Hub/ISPE/ISPE-GAMP5/figures/fig-p32-1.png",
      "used_thumb": false
    }
  ]
}